{"chunk_definitions":[{"row":9,"row_count":1,"visible":true,"expansion_state":0,"options":{"engine":"r","label":"setup","include":false},"document_id":"FB47696B","chunk_id":"csetup_chunk","chunk_label":"setup"},{"row":17,"row_count":1,"visible":true,"expansion_state":0,"options":{"engine":"r","label":"unnamed-chunk-5"},"document_id":"FB47696B","chunk_id":"cgg6lwdzfzlua","chunk_label":"unnamed-chunk-1"},{"row":27,"row_count":1,"visible":true,"expansion_state":0,"options":{"engine":"r","label":"load data"},"document_id":"FB47696B","chunk_id":"cuvo2vnd5fk16","chunk_label":"load data"},{"row":32,"row_count":1,"visible":true,"expansion_state":0,"options":{"engine":"r","label":"unnamed-chunk-7"},"document_id":"FB47696B","chunk_id":"cb3cgriqb2gd6","chunk_label":"unnamed-chunk-2"},{"row":37,"row_count":1,"visible":true,"expansion_state":0,"options":{"engine":"r","label":"unnamed-chunk-9"},"document_id":"FB47696B","chunk_id":"c5r07juttzmay","chunk_label":"unnamed-chunk-3"}],"doc_write_time":1648876516,"working_dir":null,"default_chunk_options":{"echo":true}}